clickandcollectnz/__init__.py
clickandcollectnz/__main__.py
clickandcollectnz/countdown.py
clickandcollectnz/foodstuffs.py
clickandcollectnz/store.py
clickandcollectnz-0.1.1.dist-info/LICENSE.md
clickandcollectnz-0.1.1.dist-info/METADATA
clickandcollectnz-0.1.1.dist-info/WHEEL
clickandcollectnz-0.1.1.dist-info/top_level.txt
clickandcollectnz-0.1.1.dist-info/zip-safe
clickandcollectnz-0.1.1.dist-info/RECORD
