Metadata-Version: 2.1
Name: clickandcollectnz
Version: 0.1.1
Summary: A package to get information about Click and Collect slots in NZ
Home-page: http://github.com/jesserockz/python-clickandcollectnz
Author: Jesse Hills
License: MIT
Platform: UNKNOWN
Requires-Dist: requests
Requires-Dist: beautifulsoup4
